miso_genie/__init__.py
miso_genie/miso_genie.py
miso_genie-0.1.0.dist-info/LICENSE
miso_genie-0.1.0.dist-info/METADATA
miso_genie-0.1.0.dist-info/WHEEL
miso_genie-0.1.0.dist-info/top_level.txt
miso_genie-0.1.0.dist-info/RECORD
