Metadata-Version: 2.2
Name: miso-genie
Version: 0.1.0
Summary: A culinary genie for miso-based recipe generation
Author-email: Mustafa Quraish <mustafaquraish@gmail.com>
License: Copyright (c) 2024 Mustafa Quraish
Project-URL: Homepage, https://github.com/mustafaquraish/miso-genie
Keywords: cooking,recipes,miso,food
Classifier: License :: OSI Approved :: MIT License
Classifier: Programming Language :: Python :: 3
Classifier: Topic :: Utilities
Requires-Python: >=3.8
License-File: LICENSE
